{
  "id": "appendix/references",
  "title": "References",
  "description": "Suggested reading and official docs",
  "source": "@site/docs/appendix/references.md",
  "sourceDirName": "appendix",
  "slug": "/appendix/references",
  "permalink": "/docs/appendix/references",
  "draft": false,
  "unlisted": false,
  "editUrl": "https://github.com/physical-ai-humanoid-robotics/physical-ai-humanoid-robotics-academy/edit/main/docs/appendix/references.md",
  "tags": [],
  "version": "current",
  "frontMatter": {
    "title": "References",
    "description": "Suggested reading and official docs"
  },
  "sidebar": "tutorialSidebar",
  "previous": {
    "title": "Glossary",
    "permalink": "/docs/appendix/glossary"
  },
  "next": {
    "title": "resources",
    "permalink": "/docs/appendix/resources"
  }
}